<annotation>
	<folder>annies_snickerdoodle_cinnamon_sugar</folder>
	<filename>IMG_0034.jpg</filename>
	<path>/Users/jbeallor/Documents/QMIND/GC_computerVision/GC_computer_vision/Data/train/annies_snickerdoodle_cinnamon_sugar/IMG_0034.jpg</path>
	<source>
		<database>Unknown</database>
	</source>
	<size>
		<width>2048</width>
		<height>2048</height>
		<depth>3</depth>
	</size>
	<segmented>0</segmented>
	<object>
		<name>annies_snickerdoodle_cinnamon_sugar</name>
		<pose>Unspecified</pose>
		<truncated>1</truncated>
		<difficult>0</difficult>
		<bndbox>
			<xmin>650</xmin>
			<ymin>1</ymin>
			<xmax>1197</xmax>
			<ymax>2037</ymax>
		</bndbox>
	</object>
</annotation>
